scrapscraper/__init__.py
scrapscraper/scrapscraper.py
scrapscraper-2.2.0.dist-info/METADATA
scrapscraper-2.2.0.dist-info/WHEEL
scrapscraper-2.2.0.dist-info/entry_points.txt
scrapscraper-2.2.0.dist-info/top_level.txt
scrapscraper-2.2.0.dist-info/RECORD
