Metadata-Version: 2.4
Name: scrapscraper
Version: 2.2.0
Summary: A fun Python web scraper if you need me comment on the github page lemonsrC00l is just my alt  UPDATE i have added tor scaping as a function 
Home-page: https://github.com/skelliyB/scrapscraper
Author: skelliyB/lemonsrC00l
Classifier: Programming Language :: Python :: 3
Classifier: License :: OSI Approved :: MIT License
Classifier: Operating System :: OS Independent
Requires-Python: >=3.8
Requires-Dist: requests
Requires-Dist: beautifulsoup4
Requires-Dist: colorama
Dynamic: author
Dynamic: classifier
Dynamic: description
Dynamic: description-content-type
Dynamic: home-page
Dynamic: requires-dist
Dynamic: requires-python
Dynamic: summary
